{"cameraMode":{"drawMode":0,"name":"Shaded","section":"Shading Mode"},"sceneLighting":false,"audioPlay":false,"sceneViewState":{"m_AlwaysRefresh":false,"showFog":true,"showSkybox":false,"showFlares":true,"showImageEffects":true,"showParticleSystems":true,"showVisualEffectGraphs":true,"m_FxEnabled":true},"in2DMode":false,"pivot":{"x":595.06787109375,"y":266.62860107421877,"z":16.108924865722658},"rotation":{"x":-0.03629998862743378,"y":0.00959081668406725,"z":-0.00034831478842534125,"w":-0.9992953538894653},"size":48.11373519897461,"orthographic":false}